kron_torch/.DS_Store
kron_torch/__init__.py
kron_torch/dist_kron.py
kron_torch/dist_onesidedkron.py
kron_torch/dist_test.py
kron_torch/kron.py
kron_torch/kron_test.py
kron_torch/kronos.py
kron_torch-0.3.3.dist-info/licenses/LICENSE
kron_torch-0.3.3.dist-info/WHEEL
kron_torch-0.3.3.dist-info/METADATA
kron_torch-0.3.3.dist-info/RECORD
