Metadata-Version: 2.4
Name: kron-torch
Version: 0.3.3
Summary: An implementation of PSGD Kron optimizer in PyTorch.
Keywords: python,machine learning,optimization,pytorch
Author: Evan Walters, Omead Pooladzandi, Xi-Lin Li
Requires-Python: >=3.9
Classifier: Environment :: Console
Classifier: Programming Language :: Python
Classifier: Intended Audience :: Developers
Classifier: Operating System :: OS Independent
Classifier: Programming Language :: Python :: 3
Classifier: Intended Audience :: Science/Research
Classifier: Development Status :: 4 - Beta
Classifier: Topic :: Scientific/Engineering :: Artificial Intelligence
Classifier: Topic :: Software Development :: Libraries :: Python Modules
License-File: LICENSE
Requires-Dist: torch
Requires-Dist: triton
Requires-Dist: opt-einsum
Project-URL: homepage, https://github.com/evanatyourservice/kron_torch
Project-URL: repository, https://github.com/evanatyourservice/kron_torch
